{
  "url": "https://policestationrepuk.org/Blog/why-you-need-a-criminal-law-specialist",
  "path": "/Blog/why-you-need-a-criminal-law-specialist",
  "title": "Why You Need a Criminal Law Specialist | PoliceStationRepUK",
  "headings": [
    {
      "level": 1,
      "text": "Why You Need a Criminal Law Specialist"
    },
    {
      "level": 2,
      "text": "Criminal Law Is Complex"
    },
    {
      "level": 2,
      "text": "The Difference a Specialist Makes"
    },
    {
      "level": 2,
      "text": "Police Station Expertise"
    },
    {
      "level": 2,
      "text": "Court Advocacy"
    },
    {
      "level": 2,
      "text": "When to Instruct a Specialist"
    },
    {
      "level": 2,
      "text": "Finding the Right Solicitor"
    }
  ],
  "content": "Criminal law is a specialised area that requires specific knowledge, skills, and experience. When your liberty is at stake, instructing a criminal law specialist rather than a general practitioner can make a significant difference to the outcome.\n\nCriminal Law Is Complex\n\nThe criminal justice system in England and Wales is governed by a complex body of statute, case law, codes of practice, and procedural rules. PACE and its Codes of Practice, the Criminal Procedure Rules, the Sentencing Council guidelines, the Code for Crown Prosecutors, and the substantive law of criminal offences all interact to create a system that requires specialist knowledge to navigate effectively.\n\nA solicitor who handles criminal work regularly will be familiar with these rules and how they apply in practice. A generalist may lack the detailed knowledge needed to identify procedural errors, challenge weak evidence, or advise on the best strategy.\n\nThe Difference a Specialist Makes\n\nA criminal law specialist brings experience in police station attendance, including disclosure, consultation, and interview strategy. They understand the nuances of different offence types and can anticipate the prosecution's approach. They are familiar with local courts, judges, and sentencing patterns. They know how to prepare effective bail applications and mitigation pleas. They can identify evidential weaknesses and procedural failings that a generalist might miss.\n\nPolice Station Expertise\n\nAt the police station, the quality of legal advice can determine the trajectory of the entire case. A specialist will know what to ask for in disclosure, how to assess the evidence, and how to advise on the interview strategy. They will understand the adverse inference provisions, the significance of prepared statements, and the circumstances in which no comment is appropriate.\n\nCourt Advocacy\n\nIf the case proceeds to court, a criminal law specialist will be able to conduct effective cross-examination, make legal submissions, present mitigation, and navigate the court process efficiently. For serious offences, a solicitor with higher court rights (HCA qualification) can represent you in the Crown Court as well.\n\nWhen to Instruct a Specialist\n\nYou should instruct a criminal law specialist whenever you are arrested or invited to a police interview, whenever you are charged with a criminal offence, whenever you face court proceedings for a criminal matter, and whenever you need advice about criminal records, cautions, or DBS disclosure. Do not assume a general solicitor will have the same expertise as a criminal specialist.\n\nFinding the Right Solicitor\n\nUse the PoliceStationRepUK directory to find criminal defence firms and accredited representatives in your area. Look for practitioners with specific experience in police station work and the offence type you face.",
  "links": [
    {
      "href": "/directory",
      "text": "Find a representative"
    },
    {
      "href": "/search",
      "text": "Search the directory"
    },
    {
      "href": "/Resources",
      "text": "Resources hub"
    }
  ],
  "crawledAt": "2026-03-25T00:00:00.000Z"
}