{
  "url": "https://policestationrepuk.org/Blog/getting-your-property-returned-by-the-police-in-the-uk",
  "path": "/Blog/getting-your-property-returned-by-the-police-in-the-uk",
  "title": "Getting Your Property Returned by the Police in the UK | PoliceStationRepUK",
  "headings": [
    {
      "level": 1,
      "text": "Getting Your Property Returned by the Police in the UK"
    },
    {
      "level": 2,
      "text": "When Can the Police Seize Property?"
    },
    {
      "level": 2,
      "text": "How Long Can the Police Keep Your Property?"
    },
    {
      "level": 2,
      "text": "Requesting the Return of Property"
    },
    {
      "level": 2,
      "text": "Applying to the Magistrates' Court"
    },
    {
      "level": 2,
      "text": "Specific Types of Property"
    },
    {
      "level": 2,
      "text": "Practical Steps"
    }
  ],
  "content": "If the police have seized your property during an investigation, search, or arrest, you may be wondering when and how you can get it back. The rules around police retention and return of property can be complex.\n\nWhen Can the Police Seize Property?\n\nThe police have various powers to seize property. Under section 19 of PACE, an officer who is lawfully on premises may seize anything they have reasonable grounds to believe is evidence of an offence or has been obtained in consequence of an offence. Property may also be seized during a search warrant execution, on arrest (personal property taken at the custody suite), under the Proceeds of Crime Act 2002, or under specific statutory powers relating to drugs, weapons, or vehicles.\n\nHow Long Can the Police Keep Your Property?\n\nThe police may retain seized property for as long as is necessary for the purposes of the investigation and any subsequent criminal proceedings. Under section 22 of PACE, property seized as evidence may be retained so long as is necessary in all the circumstances. If the property is no longer required for evidential purposes and no criminal proceedings are pending, the police should return it.\n\nIn practice, the police sometimes retain property for extended periods, particularly in complex investigations. If you believe the police are retaining your property without justification, you can make a formal request for its return.\n\nRequesting the Return of Property\n\nThe first step is to write to the officer in charge of the investigation or the property officer at the relevant police station. Your letter should identify the property, explain that you are the owner, request its return, and ask for an explanation if the police intend to retain it. Keep a copy of all correspondence.\n\nIf the police refuse to return your property, you can apply to the magistrates' court under section 1 of the Police (Property) Act 1897. The court has the power to make an order for the return of property if it is satisfied that the property is not required for evidential purposes and that you are the rightful owner.\n\nApplying to the Magistrates' Court\n\nAn application under the Police (Property) Act 1897 is made by way of complaint to the local magistrates' court. You will need to provide evidence of ownership and explain why the property should be returned. The police will have the opportunity to object. The court will consider the competing interests and make an order.\n\nSpecific Types of Property\n\nMobile phones and electronic devices are commonly seized during investigations. The police may retain these for analysis, which can take weeks or months. If the device is no longer required, you can request its return. Cash seized under the Proceeds of Crime Act 2002 is subject to a separate regime. The police can apply for a detention order to retain cash pending forfeiture proceedings. You may need legal representation to contest such an order. Vehicles seized under section 165 of the Road Traffic Act or section 59 of the Police Reform Act may be subject to recovery fees and storage charges.\n\nPractical Steps\n\nKeep records of what was seized, including descriptions and serial numbers. Obtain a property receipt from the police at the time of seizure. Follow up regularly. If the investigation has concluded and no proceedings are pending, press firmly for return. Seek legal advice if the police are uncooperative.",
  "links": [
    {
      "href": "/directory",
      "text": "Find a representative"
    },
    {
      "href": "/Resources",
      "text": "Resources hub"
    }
  ],
  "crawledAt": "2026-03-25T00:00:00.000Z"
}